dsoinabox/__init__.py
dsoinabox/__main__.py
dsoinabox/cli.py
dsoinabox/reporting/__init__.py
dsoinabox/reporting/checkov.py
dsoinabox/reporting/grype.py
dsoinabox/reporting/opengrep.py
dsoinabox/reporting/parser.py
dsoinabox/reporting/report_builder.py
dsoinabox/reporting/sarif_formatter.py
dsoinabox/reporting/trufflehog.py
dsoinabox/reporting/templates/html/default_checkov.html
dsoinabox/reporting/templates/html/default_grype.html
dsoinabox/reporting/templates/html/default_opengrep.html
dsoinabox/reporting/templates/html/default_syft.html
dsoinabox/reporting/templates/html/default_trufflehog.html
dsoinabox/reporting/templates/html/default_unified_report.html
dsoinabox/reporting/templates/html/dsoiab_logo_base64.txt
dsoinabox/reporting/templates/jenkins_html/default_checkov.html
dsoinabox/reporting/templates/jenkins_html/default_grype.html
dsoinabox/reporting/templates/jenkins_html/default_opengrep.html
dsoinabox/reporting/templates/jenkins_html/default_syft.html
dsoinabox/reporting/templates/jenkins_html/default_trufflehog.html
dsoinabox/reporting/templates/jenkins_html/default_unified_report.html
dsoinabox/reporting/templates/jenkins_html/assets/app.js
dsoinabox/reporting/templates/jenkins_html/assets/logo.png
dsoinabox/reporting/templates/jenkins_html/assets/styles.css
dsoinabox/scanners/__init__.py
dsoinabox/scanners/base.py
dsoinabox/scanners/iac/__init__.py
dsoinabox/scanners/iac/checkov.py
dsoinabox/scanners/sast/__init__.py
dsoinabox/scanners/sast/opengrep.py
dsoinabox/scanners/sbom/__init__.py
dsoinabox/scanners/sbom/syft.py
dsoinabox/scanners/sca/__init__.py
dsoinabox/scanners/sca/grype.py
dsoinabox/scanners/secrets/__init__.py
dsoinabox/scanners/secrets/trufflehog.py
dsoinabox/utils/deterministic.py
dsoinabox/utils/environment.py
dsoinabox/utils/git.py
dsoinabox/utils/project_id.py
dsoinabox/utils/runner.py
dsoinabox/waivers/__init__.py
dsoinabox/waivers/benchmark.py
dsoinabox/waivers/loader.py
dsoinabox/waivers/matcher.py
dsoinabox-0.1.4.dist-info/licenses/LICENSE
dsoinabox-0.1.4.dist-info/licenses/NOTICE
dsoinabox-0.1.4.dist-info/METADATA
dsoinabox-0.1.4.dist-info/WHEEL
dsoinabox-0.1.4.dist-info/entry_points.txt
dsoinabox-0.1.4.dist-info/top_level.txt
dsoinabox-0.1.4.dist-info/RECORD
