Metadata-Version: 2.4
Name: dsoinabox
Version: 0.1.4
Summary: DSO in a Box
Requires-Python: >=3.12
License-File: LICENSE
License-File: NOTICE
Requires-Dist: tabulate>=0.9.0
Requires-Dist: cyclonedx-python-lib>=11.5.0
Requires-Dist: pyyaml>=6.0.3
Requires-Dist: pydantic>=2.12.4
Requires-Dist: jinja2>=3.1.6
Provides-Extra: dev
Requires-Dist: pytest; extra == "dev"
Requires-Dist: pytest-cov; extra == "dev"
Requires-Dist: freezegun; extra == "dev"
Requires-Dist: hypothesis; extra == "dev"
Requires-Dist: syrupy; extra == "dev"
Requires-Dist: typing-extensions; extra == "dev"
Dynamic: license-file
